{"name":"Package","identifier":"5BPQVAXGXR","description":"Manage packages","parentIntentSignature":null,"sampleUtterances":[{"utterance":"I have a package"},{"utterance":"I have a delivery"},{"utterance":"I have a package for Epitech Barcelona"},{"utterance":"Where must I deliver the package ?"},{"utterance":"I have a package, where must I leave it ?"},{"utterance":"I have some packages"},{"utterance":"I am a delivery guy"}],"intentConfirmationSetting":null,"intentClosingSetting":{"isActive":true,"closingResponse":{"messageGroupsList":[{"message":{"ssmlMessage":null,"customPayload":null,"plainTextMessage":{"value":"Have a nice day !"},"imageResponseCard":null},"variations":[{"ssmlMessage":null,"customPayload":null,"plainTextMessage":{"value":"Bye !"},"imageResponseCard":null},{"ssmlMessage":null,"customPayload":null,"plainTextMessage":{"value":"Goodbye !"},"imageResponseCard":null}]}],"allowInterrupt":true}},"inputContexts":null,"outputContexts":null,"kendraConfiguration":null,"dialogCodeHook":null,"fulfillmentCodeHook":{"fulfillmentUpdatesSpecification":null,"postFulfillmentStatusSpecification":null,"enabled":true},"slotPriorities":[{"priority":1,"slotName":"dest"}]}